fx_backtester/__init__.py
fx_backtester-1.2.1.dist-info/LICENSE
fx_backtester-1.2.1.dist-info/METADATA
fx_backtester-1.2.1.dist-info/WHEEL
fx_backtester-1.2.1.dist-info/RECORD
